{
  "date": "2026-05-05",
  "generated_at": "2026-05-05T08:00:06.462211",
  "whoop": {
    "imported": true,
    "recovery": 69.0,
    "hrv": 34.8,
    "rhr": 50.0,
    "sleep_perf": 85.0,
    "strain": 4.4,
    "sleep_hrs": 7.0,
    "spo2": 92.1,
    "skin_temp": 33.9,
    "sleep_efficiency": 96.8,
    "sleep_consistency": 87.0,
    "respiratory_rate": 13.5,
    "light_sleep_hrs": 3.2,
    "deep_sleep_hrs": 2.2,
    "rem_sleep_hrs": 1.6,
    "awake_hrs": 0.2,
    "sleep_cycles": 3,
    "disturbances": 9,
    "sleep_needed_hrs": 9.6,
    "sleep_debt_hrs": 1.8,
    "calories": 615,
    "avg_hr": 54,
    "max_hr": 126,
    "workouts": []
  },
  "apple_health": {
    "imported": false
  },
  "checkin": {
    "imported": true,
    "mood": 5,
    "energy": 7,
    "sleep_quality": 8,
    "supplements": 1,
    "supplements_list": [
      {
        "name": "Enterosgel",
        "time": "06:33",
        "dose": "",
        "unit": ""
      }
    ],
    "energy_afternoon": 5,
    "energy_evening": 5,
    "anxiety": 0,
    "bloating": 0
  },
  "zoe": {
    "imported": false
  }
}